[
    {
        "segmentnr": "PA_ja_252:0.1",
        "original": "Jātaka",
        "analyzed": "jātaka ",
        "folio": "0"
    },
    {
        "segmentnr": "PA_ja_252:0.2",
        "original": "Tikanipāta",
        "analyzed": "tika nipāta ",
        "folio": "0"
    },
    {
        "segmentnr": "PA_ja_252:0.3",
        "original": "Saṅkappavagga",
        "analyzed": "saṅkappa vagga ",
        "folio": "0"
    },
    {
        "segmentnr": "PA_ja_252:0.4",
        "original": "2. Tilamuṭṭhijātaka",
        "analyzed": "tilamuṭṭhijātaka ",
        "folio": "0"
    },
    {
        "segmentnr": "PA_ja_252:1.1",
        "original": "“Ajjāpi me taṁ manasi,",
        "analyzed": "ajja api me tam manasi ",
        "folio": "1"
    },
    {
        "segmentnr": "PA_ja_252:1.2",
        "original": "yaṁ maṁ tvaṁ tilamuṭṭhiyā;",
        "analyzed": "yam mama tvam tila muṭṭhiyā ",
        "folio": "1"
    },
    {
        "segmentnr": "PA_ja_252:1.3",
        "original": "Bāhāya maṁ gahetvāna,",
        "analyzed": "bāhāya mam ",
        "folio": "1"
    },
    {
        "segmentnr": "PA_ja_252:1.4",
        "original": "laṭṭhiyā anutāḷayi.",
        "analyzed": "laṭṭhiyā anutāḷayi ",
        "folio": "1"
    },
    {
        "segmentnr": "PA_ja_252:2.1",
        "original": "Nanu jīvite na ramasi,",
        "analyzed": "nanu jīvite na ramasi ",
        "folio": "2"
    },
    {
        "segmentnr": "PA_ja_252:2.2",
        "original": "yenāsi brāhmaṇāgato;",
        "analyzed": "yena asi brāhmaṇa āgataḥ ",
        "folio": "2"
    },
    {
        "segmentnr": "PA_ja_252:2.3",
        "original": "Yaṁ maṁ bāhā gahetvāna,",
        "analyzed": "yam mam bāhā ",
        "folio": "2"
    },
    {
        "segmentnr": "PA_ja_252:2.4",
        "original": "tikkhattuṁ anutāḷayi”.",
        "analyzed": "tikkhattum anutāḍayi ",
        "folio": "2"
    },
    {
        "segmentnr": "PA_ja_252:3.1",
        "original": "“Ariyo anariyaṁ kubbantaṁ,",
        "analyzed": "ariyaḥ anariyam kubbanta ",
        "folio": "3"
    },
    {
        "segmentnr": "PA_ja_252:3.2",
        "original": "Yo daṇḍena nisedhati;",
        "analyzed": "yaḥ daṇḍena nisedhati ",
        "folio": "3"
    },
    {
        "segmentnr": "PA_ja_252:3.3",
        "original": "Sāsanaṁ taṁ na taṁ veraṁ,",
        "analyzed": "sa āsanam tam na tam vera ",
        "folio": "3"
    },
    {
        "segmentnr": "PA_ja_252:3.4",
        "original": "Iti naṁ paṇḍitā vidū”ti.",
        "analyzed": "iti nam paṇḍitā ",
        "folio": "3"
    },
    {
        "segmentnr": "PA_ja_252:4.1",
        "original": "Tilamuṭṭhijātakaṁ dutiyaṁ.",
        "analyzed": "tilamuṭṭhi jātakam ",
        "folio": "4"
    }
]