[
    {
        "segmentnr": "PA_ja_40:0.1",
        "original": "Jātaka",
        "analyzed": "jātaka ",
        "folio": "0"
    },
    {
        "segmentnr": "PA_ja_40:0.2",
        "original": "Ekakanipāta",
        "analyzed": "eka ka nipāta ",
        "folio": "0"
    },
    {
        "segmentnr": "PA_ja_40:0.3",
        "original": "Kulāvakavagga",
        "analyzed": "kulāvaka vagga ",
        "folio": "0"
    },
    {
        "segmentnr": "PA_ja_40:0.4",
        "original": "10. Khadiraṅgārajātaka",
        "analyzed": "      ",
        "folio": "0"
    },
    {
        "segmentnr": "PA_ja_40:1.1",
        "original": "“Kāmaṁ patāmi nirayaṁ,",
        "analyzed": "kāmam patāmi niraya ",
        "folio": "1"
    },
    {
        "segmentnr": "PA_ja_40:1.2",
        "original": "uddhampādo avaṁsiro;",
        "analyzed": "uddhampādaḥ avasiraḥ ",
        "folio": "1"
    },
    {
        "segmentnr": "PA_ja_40:1.3",
        "original": "Nānariyaṁ karissāmi,",
        "analyzed": "na anariyam karissāmi ",
        "folio": "1"
    },
    {
        "segmentnr": "PA_ja_40:1.4",
        "original": "handa piṇḍaṁ paṭiggahā”ti.",
        "analyzed": "handa piṇḍam paṭiggahāti ",
        "folio": "1"
    },
    {
        "segmentnr": "PA_ja_40:2.1",
        "original": "Khadiraṅgārajātakaṁ dasamaṁ.",
        "analyzed": "khadiḥ aṅgāra jātakam dasama ",
        "folio": "2"
    },
    {
        "segmentnr": "PA_ja_40:2.2",
        "original": "Kulāvakavaggo catuttho.",
        "analyzed": "kulāvaka vaggo catuttho ",
        "folio": "2"
    },
    {
        "segmentnr": "PA_ja_40:3.1",
        "original": "Tassuddānaṁ",
        "analyzed": "tassa uddāna ",
        "folio": "3"
    },
    {
        "segmentnr": "PA_ja_40:4.1",
        "original": "Sirimātali dhītara pakkhivaro,",
        "analyzed": "siri mātali pakkhi varo ",
        "folio": "4"
    },
    {
        "segmentnr": "PA_ja_40:4.2",
        "original": "Ratiyāgato mātāpitā ca puna;",
        "analyzed": "rati yāgataḥ mātā pitā ca punar ",
        "folio": "4"
    },
    {
        "segmentnr": "PA_ja_40:4.3",
        "original": "Jagatīruha vuḍḍha sukakkaṭako,",
        "analyzed": "jagatīruha vuḍḍha su kakkaṭako ",
        "folio": "4"
    },
    {
        "segmentnr": "PA_ja_40:4.4",
        "original": "Tathā nandakapiṇḍavarena dasāti.",
        "analyzed": "tathā nandaka piṇḍa varena dasāti ",
        "folio": "4"
    }
]